ag2studio/__init__.py
ag2studio/chatmanager.py
ag2studio/cli.py
ag2studio/datamodel.py
ag2studio/version.py
ag2studio/workflowmanager.py
ag2studio/database/__init__.py
ag2studio/database/alembic.ini
ag2studio/database/dbmanager.py
ag2studio/database/utils.py
ag2studio/database/migrations/README
ag2studio/database/migrations/__init__.py
ag2studio/database/migrations/env.py
ag2studio/database/migrations/script.py.mako
ag2studio/utils/__init__.py
ag2studio/utils/dbdefaults.json
ag2studio/utils/utils.py
ag2studio/web/__init__.py
ag2studio/web/app.py
ag2studio/web/ui/404.html
ag2studio/web/ui/index.html
ag2studio/web/ui/index.txt
ag2studio/web/ui/404/index.html
ag2studio/web/ui/_next/static/chunks/170-84eba9d11264fe4c.js
ag2studio/web/ui/_next/static/chunks/173-6db7e339adb73486.js
ag2studio/web/ui/_next/static/chunks/355-336fd893ffe0275b.js
ag2studio/web/ui/_next/static/chunks/440-2a1aa1576c77354d.js
ag2studio/web/ui/_next/static/chunks/4bd1b696-49d81e8785c9af86.js
ag2studio/web/ui/_next/static/chunks/517-249720c9a8f6e0ee.js
ag2studio/web/ui/_next/static/chunks/577.7191e08cbc19e1ba.js
ag2studio/web/ui/_next/static/chunks/704-79603ebc4f779523.js
ag2studio/web/ui/_next/static/chunks/981-00f50c791fd87407.js
ag2studio/web/ui/_next/static/chunks/987-ff22c7216f766156.js
ag2studio/web/ui/_next/static/chunks/framework-58f97e80b1d6e3ea.js
ag2studio/web/ui/_next/static/chunks/main-3d93416dcea5355f.js
ag2studio/web/ui/_next/static/chunks/main-app-afebdcc112e0bd66.js
ag2studio/web/ui/_next/static/chunks/polyfills-42372ed130431b0a.js
ag2studio/web/ui/_next/static/chunks/webpack-65668970400f87e1.js
ag2studio/web/ui/_next/static/chunks/app/layout-60ddaa28d22362f3.js
ag2studio/web/ui/_next/static/chunks/app/not-found-0fee00162ab673a8.js
ag2studio/web/ui/_next/static/chunks/app/page-4fbbf4d4eda2cdeb.js
ag2studio/web/ui/_next/static/chunks/app/_not-found/page-3e13321bdc604d13.js
ag2studio/web/ui/_next/static/chunks/app/build/page-cb097421288905f0.js
ag2studio-0.0.1rc5.dist-info/LICENSE
ag2studio-0.0.1rc5.dist-info/METADATA
ag2studio-0.0.1rc5.dist-info/WHEEL
ag2studio-0.0.1rc5.dist-info/entry_points.txt
ag2studio-0.0.1rc5.dist-info/top_level.txt
ag2studio-0.0.1rc5.dist-info/RECORD
