Metadata-Version: 2.2
Name: ag2studio
Version: 0.0.1rc5
Summary: AG2 Studio
Author-email: Chi Wang & Jingyun Wu <support@ag2.ai>
License:                                  Apache License
Project-URL: Homepage, https://github.com/ag2ai/ag2
Project-URL: Bug Tracker, https://github.com/ag2ai/ag2/issues
Classifier: Programming Language :: Python :: 3
Classifier: License :: OSI Approved :: Apache Software License
Classifier: Operating System :: OS Independent
Requires-Python: >=3.9
License-File: LICENSE
Requires-Dist: pydantic
Requires-Dist: fastapi
Requires-Dist: typer
Requires-Dist: uvicorn
Requires-Dist: arxiv
Requires-Dist: ag2[gemini]>=0.2.0
Requires-Dist: python-dotenv
Requires-Dist: websockets
Requires-Dist: numpy>=2.1.0
Requires-Dist: sqlmodel
Requires-Dist: psycopg
Requires-Dist: alembic
Requires-Dist: loguru
Provides-Extra: web
Requires-Dist: fastapi; extra == "web"
Requires-Dist: uvicorn; extra == "web"
Provides-Extra: database
Requires-Dist: psycopg; extra == "database"
Provides-Extra: all
Requires-Dist: ag2studio[web]; extra == "all"
Requires-Dist: ag2studio[database]; extra == "all"
